gmpyinfr_log/__init__.py
gmpyinfr_log/dsgpttn/__init__.py
gmpyinfr_log/dsgpttn/singleton.py
gmpyinfr_log/log/__init__.py
gmpyinfr_log/log/base.py
gmpyinfr_log/log/kibana.py
gmpyinfr_log/utils/__init__.py
gmpyinfr_log-0.0.1.dist-info/LICENSE
gmpyinfr_log-0.0.1.dist-info/METADATA
gmpyinfr_log-0.0.1.dist-info/WHEEL
gmpyinfr_log-0.0.1.dist-info/top_level.txt
gmpyinfr_log-0.0.1.dist-info/RECORD
